pytorch_volumetric/__init__.py
pytorch_volumetric/chamfer.py
pytorch_volumetric/model_to_sdf.py
pytorch_volumetric/sdf.py
pytorch_volumetric/visualization.py
pytorch_volumetric/volume.py
pytorch_volumetric/voxel.py
pytorch_volumetric-0.5.3.dist-info/LICENSE.txt
pytorch_volumetric-0.5.3.dist-info/METADATA
pytorch_volumetric-0.5.3.dist-info/WHEEL
pytorch_volumetric-0.5.3.dist-info/top_level.txt
pytorch_volumetric-0.5.3.dist-info/RECORD
