Metadata-Version: 2.1
Name: pytorch-volumetric
Version: 0.5.3
Summary: Volumetric structures such as voxels and SDFs implemented in pytorch
Author-email: Sheng Zhong <zhsh@umich.edu>
Maintainer-email: Sheng Zhong <zhsh@umich.edu>
License: Copyright (c) 2023 University of Michigan ARM Lab
Project-URL: Homepage, https://github.com/UM-ARM-Lab/pytorch_volumetric
Project-URL: Bug Reports, https://github.com/UM-ARM-Lab/pytorch_volumetric/issues
Project-URL: Source, https://github.com/UM-ARM-Lab/pytorch_volumetric
Keywords: robotics,sdf,voxels,pytorch
Classifier: Development Status :: 4 - Beta
Classifier: Intended Audience :: Developers
Classifier: License :: OSI Approved :: MIT License
Classifier: Programming Language :: Python :: 3
Classifier: Programming Language :: Python :: 3 :: Only
Requires-Python: >=3.6
License-File: LICENSE.txt
Requires-Dist: torch
Requires-Dist: numpy
Requires-Dist: open3d
Requires-Dist: arm-pytorch-utilities >=0.4
Requires-Dist: multidim-indexing
Requires-Dist: pytorch-kinematics >=0.5.6
Provides-Extra: test
Requires-Dist: pytest ; extra == 'test'
Requires-Dist: pybullet ; extra == 'test'
